epftoolbox2/__init__.py
epftoolbox2/logging.py
epftoolbox2/data/cache_manager.py
epftoolbox2/data/sources/__init__.py
epftoolbox2/data/sources/base.py
epftoolbox2/data/sources/calendar.py
epftoolbox2/data/sources/csv.py
epftoolbox2/data/sources/entsoe.py
epftoolbox2/data/sources/open_meteo.py
epftoolbox2/data/transformers/__init__.py
epftoolbox2/data/transformers/base.py
epftoolbox2/data/transformers/lag.py
epftoolbox2/data/transformers/resample.py
epftoolbox2/data/transformers/timezone.py
epftoolbox2/data/validators/__init__.py
epftoolbox2/data/validators/base.py
epftoolbox2/data/validators/continuity.py
epftoolbox2/data/validators/eda.py
epftoolbox2/data/validators/null_check.py
epftoolbox2/data/validators/result.py
epftoolbox2/evaluators/__init__.py
epftoolbox2/evaluators/base.py
epftoolbox2/evaluators/mae.py
epftoolbox2/exporters/__init__.py
epftoolbox2/exporters/base.py
epftoolbox2/exporters/excel.py
epftoolbox2/exporters/terminal.py
epftoolbox2/models/__init__.py
epftoolbox2/models/base.py
epftoolbox2/models/lasso.py
epftoolbox2/models/ols.py
epftoolbox2/pipelines/__init__.py
epftoolbox2/pipelines/data_pipeline.py
epftoolbox2/pipelines/model_pipeline.py
epftoolbox2/results/__init__.py
epftoolbox2/results/report.py
epftoolbox2/results/store.py
epftoolbox2/scalers/__init__.py
epftoolbox2/scalers/standard.py
epftoolbox2-2.0.0a3.dist-info/METADATA
epftoolbox2-2.0.0a3.dist-info/WHEEL
epftoolbox2-2.0.0a3.dist-info/licenses/LICENSE
epftoolbox2-2.0.0a3.dist-info/RECORD
