Metadata-Version: 2.4
Name: epftoolbox2
Version: 2.0.0a3
Summary: Energy Price Forecasting Toolbox 2
Project-URL: Homepage, https://github.com/dawidlinek/epftoolbox2
Project-URL: Documentation, https://dawidlinek.github.io/epftoolbox2
Project-URL: Repository, https://github.com/dawidlinek/epftoolbox2
Project-URL: Issues, https://github.com/dawidlinek/epftoolbox2/issues
Author-email: Dawid Linek <dawid@linek.dev>
License: GPL-3.0
License-File: LICENSE
Keywords: deep learning,electricity price,energy,forecasting,machine learning,toolbox
Classifier: Development Status :: 3 - Alpha
Classifier: Intended Audience :: Science/Research
Classifier: License :: OSI Approved :: GNU General Public License v3 (GPLv3)
Classifier: Operating System :: OS Independent
Classifier: Programming Language :: Python :: 3
Classifier: Programming Language :: Python :: 3.10
Classifier: Programming Language :: Python :: 3.11
Classifier: Programming Language :: Python :: 3.12
Classifier: Programming Language :: Python :: 3.13
Classifier: Programming Language :: Python :: 3.14
Classifier: Topic :: Scientific/Engineering
Requires-Python: >=3.10
Requires-Dist: astral>=3.2
Requires-Dist: beautifulsoup4>=4.12.0
Requires-Dist: holidays>=0.40
Requires-Dist: numpy>=2.2.0
Requires-Dist: openpyxl>=3.1.0
Requires-Dist: pandas>=2.0.0
Requires-Dist: pyyaml>=6.0.0
Requires-Dist: requests>=2.31.0
Requires-Dist: rich>=13.0.0
Requires-Dist: scikit-learn>=1.3.0
Provides-Extra: dev
Requires-Dist: pytest-cov>=4.1.0; extra == 'dev'
Requires-Dist: pytest>=7.4.0; extra == 'dev'
Requires-Dist: ruff>=0.1.0; extra == 'dev'
